{
  "showDialog": true,
  "versionCode": 3059966944,
  "versionName": "30.34.37",
  "forceUpdate": true,
  "changelogTitle": "Вышло новое обновление",
  "changelog": "\n☰ Что нового: ↓\n\n1- Исправлены ошибки.\n\n2- Повышена плавность и производительность.\n\n3- Обновление до последней версии.\n\n📱 Больше приложений на @utgram.\n\n→ Спасибо, что используешь наши моды ❤️",
  "patchedBy": "UtGram",
  "updateButtonText": "Обновить",
  "laterButtonText": "Позже",
  "updateUrl": "https://t.me/utgram"
}
